fmu/__init__.py
fmu/ensemble/.gitignore
fmu/ensemble/__init__.py
fmu/ensemble/ensemble.py
fmu/ensemble/ensemblecombination.py
fmu/ensemble/ensembleset.py
fmu/ensemble/etc.py
fmu/ensemble/observations.py
fmu/ensemble/realization.py
fmu/ensemble/realizationcombination.py
fmu/ensemble/version.py
fmu/ensemble/virtualensemble.py
fmu/ensemble/virtualrealization.py
fmu/ensemble/util/__init__.py
fmu/ensemble/util/dates.py
fmu/ensemble/util/rates.py
fmu_ensemble-1.6.11.dist-info/licenses/AUTHORS.rst
fmu_ensemble-1.6.11.dist-info/licenses/LICENSE
fmu_ensemble-1.6.11.dist-info/METADATA
fmu_ensemble-1.6.11.dist-info/WHEEL
fmu_ensemble-1.6.11.dist-info/top_level.txt
fmu_ensemble-1.6.11.dist-info/RECORD
