Metadata-Version: 2.4
Name: fmu-ensemble
Version: 1.6.11
Summary: Python API to ensembles produced by ERT
Author-email: Håvard Berland <havb@equinor.com>
License: GPL-3.0
Project-URL: Repository, https://github.com/equinor/fmu-ensemble
Keywords: fmu,ensemble
Classifier: Development Status :: 5 - Production/Stable
Classifier: Intended Audience :: Developers
Classifier: Natural Language :: English
Classifier: Programming Language :: Python :: 3
Classifier: Programming Language :: Python :: 3.11
Classifier: Programming Language :: Python :: 3.12
Requires-Python: >=3.8
License-File: LICENSE
License-File: AUTHORS.rst
Requires-Dist: resdata>=4.0.0
Requires-Dist: numpy
Requires-Dist: pandas
Requires-Dist: pyyaml>=5.1
Provides-Extra: test
Requires-Dist: pytest>=2.9.2; extra == "test"
Requires-Dist: pytest-cov; extra == "test"
Provides-Extra: docs
Requires-Dist: ipython; extra == "docs"
Requires-Dist: rstcheck; extra == "docs"
Requires-Dist: sphinx; extra == "docs"
Requires-Dist: sphinx-argparse; extra == "docs"
Requires-Dist: sphinx_rtd_theme; extra == "docs"
Provides-Extra: style
Requires-Dist: pre-commit; extra == "style"
Provides-Extra: parquet
Requires-Dist: pyarrow; extra == "parquet"
Dynamic: license-file
